gopem/__init__.py
gopem/__main__.py
gopem/helper.py
gopem/mainwindow.py
gopem/plotter.py
gopem-0.8.dist-info/AUTHORS.md
gopem-0.8.dist-info/LICENSE
gopem-0.8.dist-info/METADATA
gopem-0.8.dist-info/WHEEL
gopem-0.8.dist-info/entry_points.txt
gopem-0.8.dist-info/top_level.txt
gopem-0.8.dist-info/RECORD
