Metadata-Version: 2.1
Name: gopem
Version: 0.8
Summary: GOPEM is a graphical user interface of OPEM
Home-page: https://github.com/ecsim/gopem
Download-URL: https://github.com/ecsim/gopem/tarball/v0.8
Author: ECSIM Development Team
Author-email: opem@ecsim.site
License: MIT
Project-URL: Webpage, http://opem.ecsim.site
Project-URL: Source, https://github.com/ecsim/gopem
Keywords: OPEM PEM FC CELL Fuel-Cell Chemistry GUI PyQt GOPEM
Platform: any
Classifier: Development Status :: 4 - Beta
Classifier: Intended Audience :: End Users/Desktop
Classifier: License :: OSI Approved :: MIT License
Classifier: Operating System :: OS Independent
Classifier: Programming Language :: Python :: 3.12
Classifier: Programming Language :: Python :: 3.11
Classifier: Programming Language :: Python :: 3.10
Classifier: Programming Language :: Python :: 3.9
Classifier: Programming Language :: Python :: 3.8
Classifier: Programming Language :: Python :: 3.7
Classifier: Programming Language :: Python :: 3.6
Classifier: Topic :: Scientific/Engineering :: Chemistry
Classifier: Topic :: Scientific/Engineering :: Physics
Requires-Python: >=3.6
License-File: LICENSE
License-File: AUTHORS.md
Requires-Dist: art >0.7
Requires-Dist: requests >=2.20.0
Requires-Dist: matplotlib >=2.2.2
Requires-Dist: PyQt5 >=5.10
Requires-Dist: PyQt5-sip >=4.19.12
Requires-Dist: opem >=0.9
